.flake8
.gitignore
LICENSE
MANIFEST.in
PUBLISH.md
README.md
pyproject.toml
setup.py
.github/workflows/publish-to-pypi.yml
.github/workflows/python-package.yml
unik/__init__.py
unik/version.py
unik.egg-info/PKG-INFO
unik.egg-info/SOURCES.txt
unik.egg-info/dependency_links.txt
unik.egg-info/requires.txt
unik.egg-info/top_level.txt
unik/tests/__init__.py
unik/tests/test_unik.py