Metadata-Version: 2.4
Name: unik
Version: 0.2.1
Summary: Provide functionality for working with selections of unique items in lists / arrays
Author-email: Gabriel Brammer <gbrammer@gmail.com>
License: MIT License
Project-URL: Homepage, https://github.com/gbrammer/unik
Project-URL: Repository, https://github.com/gbrammer/unik
Project-URL: Issues, https://github.com/gbrammer/unik/issues
Classifier: Development Status :: 3 - Alpha
Classifier: Intended Audience :: Developers
Classifier: Programming Language :: Python :: 3
Classifier: Programming Language :: Python :: 3.8
Classifier: Programming Language :: Python :: 3.9
Classifier: Programming Language :: Python :: 3.10
Classifier: Programming Language :: Python :: 3.11
Classifier: Programming Language :: Python :: 3.12
Requires-Python: >=3.8
License-File: LICENSE
Requires-Dist: numpy
Provides-Extra: test
Requires-Dist: pytest>=7.0; extra == "test"
Requires-Dist: build>=0.10.0; extra == "test"
Requires-Dist: twine>=4.0.0; extra == "test"
Requires-Dist: flake8; extra == "test"
Dynamic: license-file
